jenkins_mcp/__init__.py
jenkins_mcp/server.py
mseep_jenkins_mcp-0.1.5.dist-info/licenses/LICENSE
mseep_jenkins_mcp-0.1.5.dist-info/METADATA
mseep_jenkins_mcp-0.1.5.dist-info/WHEEL
mseep_jenkins_mcp-0.1.5.dist-info/entry_points.txt
mseep_jenkins_mcp-0.1.5.dist-info/top_level.txt
mseep_jenkins_mcp-0.1.5.dist-info/RECORD
